epub_text_extractor/__init__.py
epub_text_extractor/cli.py
epub_text_extractor/converter.py
epub_text_extractor/extractor.py
epub_text_extractor/reader.py
epub_text_extractor/setup.py
epub_text_extractor-0.1.0.dist-info/METADATA
epub_text_extractor-0.1.0.dist-info/WHEEL
epub_text_extractor-0.1.0.dist-info/entry_points.txt
epub_text_extractor-0.1.0.dist-info/top_level.txt
epub_text_extractor-0.1.0.dist-info/RECORD
