Metadata-Version: 2.1
Name: epub_text_extractor
Version: 0.1.0
Summary: A Python package to extract text from EPUB files
Author: Your Name
Author-email: your.email@example.com
Classifier: Programming Language :: Python :: 3
Classifier: License :: OSI Approved :: MIT License
Classifier: Operating System :: OS Independent
Requires-Python: >=3.6
Requires-Dist: ebooklib
Requires-Dist: beautifulsoup4
Requires-Dist: markdown
